cronpi/__init__.py
cronpi/app.py
cronpi/cron.py
cronpi/validator.py
test/__init__.py
test/test_normal.py
test/test_validation.py
cronpi-2.0.1.dist-info/LICENSE
cronpi-2.0.1.dist-info/METADATA
cronpi-2.0.1.dist-info/WHEEL
cronpi-2.0.1.dist-info/top_level.txt
cronpi-2.0.1.dist-info/RECORD
