Metadata-Version: 2.1
Name: cronpi
Version: 2.0.1
Summary: a small crontab deploying package for python
Home-page: https://github.com/dakc/cronpi
Author: dakc
Author-email: dakc@outlook.jp
License: UNKNOWN
Platform: UNKNOWN
Classifier: Programming Language :: Python 
Classifier: License :: OSI Approved :: MIT License
Classifier: Operating System :: POSIX :: Linux
